vulpai/__init__.py
vulpai/api/__init__.py
vulpai/api/auth.py
vulpai/api/client.py
vulpai/api/endpoints.py
vulpai/client.py
vulpai/config.py
vulpai/exceptions.py
vulpai/models/__init__.py
vulpai/models/artifact.py
vulpai/models/credit.py
vulpai/models/response.py
vulpai/models/validation.py
vulpai/uploaders/__init__.py
vulpai/uploaders/base.py
vulpai/uploaders/dataset_uploader.py
vulpai/uploaders/model_uploader.py
vulpai/utils/__init__.py
vulpai/utils/compression.py
vulpai/utils/crypto.py
vulpai/utils/metadata.py
vulpai/utils/progress.py
vulpai/validators/__init__.py
vulpai/validators/base.py
vulpai/validators/custom_validator.py
vulpai/validators/pytorch_validator.py
vulpai/validators/sklearn_validator.py
vulpai/validators/tensorflow_validator.py
vulpai-1.0.5.dist-info/METADATA
vulpai-1.0.5.dist-info/WHEEL
vulpai-1.0.5.dist-info/RECORD
