Metadata-Version: 2.3
Name: vulpai
Version: 1.0.5
Summary: Sistema de Validação de Modelos de IA com integração Claude API
License: MIT
Keywords: ai,machine-learning,validation,model-validation,claude-api
Author: VulpAI Team
Author-email: contato@vulpai.com
Requires-Python: >=3.10,<3.13
Classifier: Development Status :: 4 - Beta
Classifier: Environment :: Console
Classifier: Intended Audience :: Developers
Classifier: Intended Audience :: Science/Research
Classifier: License :: OSI Approved :: MIT License
Classifier: Natural Language :: Portuguese (Brazilian)
Classifier: Programming Language :: Python :: 3
Classifier: Programming Language :: Python :: 3.10
Classifier: Programming Language :: Python :: 3.11
Classifier: Programming Language :: Python :: 3.12
Classifier: Topic :: Scientific/Engineering :: Artificial Intelligence
Provides-Extra: all
Provides-Extra: onnx
Provides-Extra: pytorch
Provides-Extra: sklearn
Provides-Extra: tensorflow
Provides-Extra: xgboost
Requires-Dist: boto3 (>=1.38.36,<2.0.0)
Requires-Dist: joblib (>=1.4.2,<2.0.0)
Requires-Dist: numpy (>=2.2.3,<3.0.0)
Requires-Dist: onnx (>=1.15.0,<2.0.0) ; extra == "onnx" or extra == "all"
Requires-Dist: pandas (>=2.2.3,<3.0.0)
Requires-Dist: pyarrow (>=19.0.1,<20.0.0)
Requires-Dist: pydantic (>=2.5.0,<3.0.0)
Requires-Dist: python-magic (>=0.4.27,<0.5.0)
Requires-Dist: requests (>=2.31.0,<3.0.0)
Requires-Dist: requests-toolbelt (>=1.0.0,<2.0.0)
Requires-Dist: rich (>=13.9.4,<14.0.0)
Requires-Dist: scikit-learn (>=1.6.1,<2.0.0) ; extra == "sklearn" or extra == "all"
Requires-Dist: torch (>=2.0.0,<3.0.0) ; extra == "pytorch" or extra == "all"
Requires-Dist: typer[all] (>=0.15.1,<0.16.0)
Requires-Dist: xgboost (>=2.1.4,<3.0.0) ; extra == "xgboost" or extra == "all"
Project-URL: Bug Tracker, https://github.com/vulpai/vulpai-python/issues
Project-URL: Changelog, https://github.com/vulpai/vulpai-python/blob/main/CHANGELOG.md
Project-URL: Documentation, https://docs.vulpai.com
Project-URL: Homepage, https://vulpai.com
Project-URL: Repository, https://github.com/vulpai/vulpai-python
